simonpackage/__about__.py
simonpackage/__init__.py
simonpackage/av/__init__.py
simonpackage/av/tts.py
simonpackage/machine_learning/__init__.py
simonpackage/misc/__init__.py
simonpackage/misc/color.py
simonpackage/misc/digits.py
simonpackage/misc/fonts.py
simonpackage/misc/mail.py
simonpackage/misc/text.py
simonpackage/misc/time.py
simonpackage/rw/__init__.py
simonpackage/spider/__init__.py
simonpackage/spider/dp.py
simonpackage/spider/request.py
simonpackage/spider/sele.py
simonpackage/system/__init__.py
simonpackage/work/__init__.py
simonpackage-0.0.1.dist-info/METADATA
simonpackage-0.0.1.dist-info/WHEEL
simonpackage-0.0.1.dist-info/licenses/LICENSE.txt
simonpackage-0.0.1.dist-info/RECORD
